{
  "logic": "nm",
  "rule": "DRI_MT",
  "depth": "d2",
  "hardening": {
    "type": "tautological",
    "k": 4,
    "seed": 42
  },
  "samples": [
    {
      "id": 1,
      "context": "Not false or false is true. Not true is false. False is not true. Not true and false is false. John and Kate are students in the same class. Usually students in that class play a sport. John does not play a sport. Kate sings in the school choir.",
      "question": "Can we conclude Kate does not sing in the school choir?",
      "answer": "no",
      "perturbation": {
        "type": "tautological",
        "k": 4,
        "injected_sentences": [
          "Not false or false is true.",
          "Not true is false.",
          "False is not true.",
          "Not true and false is false."
        ]
      }
    },
    {
      "id": 2,
      "context": "True is not false. True and false is not true. False and true is not true. True or not true is true. The red car and blue car are both sedans. Sedans normally have leather seats. The red car does not have leather seats. The blue car has a sunroof.",
      "question": "Can we conclude the blue car does not have a sunroof?",
      "answer": "no",
      "perturbation": {
        "type": "tautological",
        "k": 4,
        "injected_sentences": [
          "True is not false.",
          "True and false is not true.",
          "False and true is not true.",
          "True or not true is true."
        ]
      }
    },
    {
      "id": 3,
      "context": "Not false and false is false. False or not false is true. False or not true is false. Not true is false. Sara and Emma work at the same company. Employees at that company typically take public transit to work. Sara drives her car to work. Emma brings her lunch everyday.",
      "question": "Can we conclude Emma does not bring her lunch everyday?",
      "answer": "no",
      "perturbation": {
        "type": "tautological",
        "k": 4,
        "injected_sentences": [
          "Not false and false is false.",
          "False or not false is true.",
          "False or not true is false.",
          "Not true is false."
        ]
      }
    },
    {
      "id": 4,
      "context": "Not true and false is false. Not false and false is false. True or true is true. Not false is true. Matt and Jacob are on the basketball team. Players on the basketball team usually attend morning practices. Matt does not attend morning practices. Jacob has a part-time job after school.",
      "question": "Can we conclude Jacob does not have a part-time job after school?",
      "answer": "no",
      "perturbation": {
        "type": "tautological",
        "k": 4,
        "injected_sentences": [
          "Not true and false is false.",
          "Not false and false is false.",
          "True or true is true.",
          "Not false is true."
        ]
      }
    },
    {
      "id": 5,
      "context": "Not false is true. Not false and true is true. True is not false. Not true or false is not true. The oak tree and pine tree are both in the park. Trees in the park generally lose their leaves in the fall. The oak tree does not lose its leaves in the fall. The pine tree provides shade.",
      "question": "Can we conclude the pine tree does not provide shade?",
      "answer": "no",
      "perturbation": {
        "type": "tautological",
        "k": 4,
        "injected_sentences": [
          "Not false is true.",
          "Not false and true is true.",
          "True is not false.",
          "Not true or false is not true."
        ]
      }
    },
    {
      "id": 6,
      "context": "True and not false is true. Not false is true. Not false and false is false. False or not true is false. John and Mary are classmates. Normally classmates sit together at lunch. John does not sit with Mary at lunch. Billy plays basketball with John.",
      "question": "Can we conclude Billy plays basketball with Mary?",
      "answer": "no",
      "perturbation": {
        "type": "tautological",
        "k": 4,
        "injected_sentences": [
          "True and not false is true.",
          "Not false is true.",
          "Not false and false is false.",
          "False or not true is false."
        ]
      }
    },
    {
      "id": 7,
      "context": "False or not true is false. True and true is not false. False and true is not true. True and false is not true. Cats and dogs are animals. Normally animals can swim. Cats cannot swim. Dogs have fur coats.",
      "question": "Can we conclude dogs do not have fur coats?",
      "answer": "no",
      "perturbation": {
        "type": "tautological",
        "k": 4,
        "injected_sentences": [
          "False or not true is false.",
          "True and true is not false.",
          "False and true is not true.",
          "True and false is not true."
        ]
      }
    },
    {
      "id": 8,
      "context": "Not false is true. True and not false is true. Not false and false is false. Not true is false. Apples and oranges are fruits. Normally fruits are sweet. Apples are not sweet. Oranges contain vitamin C.",
      "question": "Can we conclude oranges do not contain vitamin C?",
      "answer": "no",
      "perturbation": {
        "type": "tautological",
        "k": 4,
        "injected_sentences": [
          "Not false is true.",
          "True and not false is true.",
          "Not false and false is false.",
          "Not true is false."
        ]
      }
    },
    {
      "id": 9,
      "context": "True or true is true. Not true and false is false. True and not false is true. Not false or false is true. Tigers and lions are felines. Normally felines hunt at night. Tigers do not hunt at night. Lions live in prides.",
      "question": "Can we conclude lions do not live in prides?",
      "answer": "no",
      "perturbation": {
        "type": "tautological",
        "k": 4,
        "injected_sentences": [
          "True or true is true.",
          "Not true and false is false.",
          "True and not false is true.",
          "Not false or false is true."
        ]
      }
    },
    {
      "id": 10,
      "context": "Not true and true is false. False or not false is true. False or not true is false. False and not true is false. Oaks and maples are trees. Normally trees lose leaves in winter.  Oaks do not lose leaves in winter. Maples have winged fruit.",
      "question": "Can we conclude maples do not have winged fruit?",
      "answer": "no",
      "perturbation": {
        "type": "tautological",
        "k": 4,
        "injected_sentences": [
          "Not true and true is false.",
          "False or not false is true.",
          "False or not true is false.",
          "False and not true is false."
        ]
      }
    },
    {
      "id": 11,
      "context": "Not true and false is false. True is not false. False or not false is true. True or true is true. Anna and Bob are students in the same class. Students in that class normally take an exam at the end. Anna did not take the exam. Bob took extra credit work.",
      "question": "Can we conclude Bob did not do the extra credit work?",
      "answer": "no",
      "perturbation": {
        "type": "tautological",
        "k": 4,
        "injected_sentences": [
          "Not true and false is false.",
          "True is not false.",
          "False or not false is true.",
          "True or true is true."
        ]
      }
    },
    {
      "id": 12,
      "context": "Not true or true is true. False and not false is false. True or not true is true. False or not false is true. The red car and blue car are both sedans. Sedans typically have power windows. The red car does not have power windows. The blue car has a sunroof.",
      "question": "Can we conclude the blue car does not have a sunroof?",
      "answer": "no",
      "perturbation": {
        "type": "tautological",
        "k": 4,
        "injected_sentences": [
          "Not true or true is true.",
          "False and not false is false.",
          "True or not true is true.",
          "False or not false is true."
        ]
      }
    },
    {
      "id": 13,
      "context": "False and true is not true. True or not true is true. False or not true is false. True and false is not true. Emma and Jacob are athletes on the school soccer team. Players are usually required to attend practices. Emma did not attend practices. Jacob volunteered at the animal shelter over the summer.",
      "question": "Can we conclude Jacob did not volunteer at the animal shelter?",
      "answer": "no",
      "perturbation": {
        "type": "tautological",
        "k": 4,
        "injected_sentences": [
          "False and true is not true.",
          "True or not true is true.",
          "False or not true is false.",
          "True and false is not true."
        ]
      }
    },
    {
      "id": 14,
      "context": "Not false is true. False and not false is false. False and true is not true. True and false is not true. Samsung and Apple both make smartphones. Smartphones these days normally have multiple cameras. The Samsung does not have multiple cameras. The Apple has a folding screen.",
      "question": "Can we conclude the Apple does not have a folding screen?",
      "answer": "no",
      "perturbation": {
        "type": "tautological",
        "k": 4,
        "injected_sentences": [
          "Not false is true.",
          "False and not false is false.",
          "False and true is not true.",
          "True and false is not true."
        ]
      }
    },
    {
      "id": 15,
      "context": "False or not true is false. False is not true. True or true is true. Not false or false is true. The oak tree and pine tree are both evergreens. Evergreens typically stay green all year. The oak tree does not stay green all year. The pine tree has grown very tall this year.",
      "question": "Can we conclude the pine tree did not grow very tall this year?",
      "answer": "no",
      "perturbation": {
        "type": "tautological",
        "k": 4,
        "injected_sentences": [
          "False or not true is false.",
          "False is not true.",
          "True or true is true.",
          "Not false or false is true."
        ]
      }
    },
    {
      "id": 16,
      "context": "True is not false. True and not false is true. Not true or false is not true. Not true or true is true. John and Mary are students in math class. Normally students in math class do homework every night. John did not do his homework last night. Mary studied extra problems that were not assigned.",
      "question": "Can we conclude Mary did not study the extra problems?",
      "answer": "no",
      "perturbation": {
        "type": "tautological",
        "k": 4,
        "injected_sentences": [
          "True is not false.",
          "True and not false is true.",
          "Not true or false is not true.",
          "Not true or true is true."
        ]
      }
    },
    {
      "id": 17,
      "context": "Not true or false is not true. False and not false is false. Not false or false is true. True is not false. The Red Sox and Yankees are baseball teams. Typically baseball teams have 9 players on the field. The Red Sox only had 8 players yesterday due to an injury. The Yankees scored 6 runs.",
      "question": "Can we conclude the Yankees did not score 6 runs?",
      "answer": "no",
      "perturbation": {
        "type": "tautological",
        "k": 4,
        "injected_sentences": [
          "Not true or false is not true.",
          "False and not false is false.",
          "Not false or false is true.",
          "True is not false."
        ]
      }
    },
    {
      "id": 18,
      "context": "Not true and true is false. Not false is true. Not false or false is true. True or not true is true. Samsung and Apple make smartphones. Usually smartphones have internet capability. The Samsung phone does not connect to internet. The Apple phone has wireless charging.",
      "question": "Can we conclude the Apple phone does not have wireless charging?",
      "answer": "no",
      "perturbation": {
        "type": "tautological",
        "k": 4,
        "injected_sentences": [
          "Not true and true is false.",
          "Not false is true.",
          "Not false or false is true.",
          "True or not true is true."
        ]
      }
    },
    {
      "id": 19,
      "context": "True and false is not true. Not true or false is not true. False and true is not true. Not true and false is false. Emma and Noah are taking an exam. Normally students taking an exam are not allowed to use notes. Emma did not use notes during exam. Noah received extra time to complete the exam.",
      "question": "Can we conclude Noah did not receive extra time on the exam?",
      "answer": "no",
      "perturbation": {
        "type": "tautological",
        "k": 4,
        "injected_sentences": [
          "True and false is not true.",
          "Not true or false is not true.",
          "False and true is not true.",
          "Not true and false is false."
        ]
      }
    },
    {
      "id": 20,
      "context": "True or true is true. False and not true is false. False or not true is false. False and not false is false. The Honda and Toyota are car models. Typically car models come with air conditioning. The Honda does not have air conditioning. The Toyota comes with leather seats.",
      "question": "Can we conclude the Toyota does not come with leather seats?",
      "answer": "no",
      "perturbation": {
        "type": "tautological",
        "k": 4,
        "injected_sentences": [
          "True or true is true.",
          "False and not true is false.",
          "False or not true is false.",
          "False and not false is false."
        ]
      }
    }
  ]
}